rladv/__init__.py
rladv/plot.py
rladv-0.0.3.dist-info/METADATA
rladv-0.0.3.dist-info/WHEEL
rladv-0.0.3.dist-info/licenses/LICENSE
rladv-0.0.3.dist-info/RECORD
