Metadata-Version: 2.3
Name: rladv
Version: 0.0.3
Summary: A simple plotter for comparing two reinforcement learning algorithms on multiple environments
Project-URL: Homepage, https://github.com/BobMak/rladv
Project-URL: Issues, https://github.com/BobMak/rladv/issues
Author-email: Volodymyr Makarenko <vlmr.mko@gmail.com>
License-File: LICENSE
Classifier: License :: OSI Approved :: MIT License
Classifier: Operating System :: OS Independent
Classifier: Programming Language :: Python :: 3
Requires-Python: >=3.8
